{
  "coupon": [
    {
      "id": 1,
      "vendor": "swatch",
      "getedCount": 100,
      "geted": false,
      "discount": 100,
      "dueDate": "2020/03/15",
      "count": 100
    },
    {
      "id": 2,
      "vendor": "swatch",
      "getedCount": 95,
      "geted": true,
      "discount": 200,
      "dueDate": "2020/03/15",
      "count": 100
    },
    {
      "id": 3,
      "vendor": "swatch",
      "getedCount": 95,
      "geted": true,
      "discount": 300,
      "dueDate": "2020/03/15",
      "count": 100
    },
    {
      "id": 4,
      "vendor": "swatch",
      "getedCount": 65,
      "geted": true,
      "discount": 400,
      "dueDate": "2020/03/15",
      "count": 100
    },
    {
      "id": 5,
      "vendor": "swatch",
      "getedCount": 10,
      "geted": false,
      "discount": 500,
      "dueDate": "2020/03/15",
      "count": 100
    },
    {
      "id": 6,
      "vendor": "swatch",
      "getedCount": 10,
      "geted": false,
      "discount": 600,
      "dueDate": "2020/03/15",
      "count": 100
    }
  ]
}